Workbook

Sheet CENTRO DE CUSTO
B1: CENTRO | C1: DEPARTAMENTO | D1: LOCAL | E1: SUPERVISOR
B2: 28000 | C2: 28 | D2: ADMINISTRATIVO - LONDRINA | E2: DENISE
B3: 76000 | C3: 76 | D3: P.M DE APUCARANA - VARRIÇÃO | E3: ROGÉRIO
B4: 76001 | C4: 76 | D4: P.M DE APUCARANA - COLETA | E4: ROGÉRIO
B5: 87200 | C5: 87 | D5: ED.LONDRINA - EQUIPE | E5: PAULO TORRES
B6: 87481 | C6: 87 | D6: ED.LONDRINA - ENCARREGADOS | E6: PAULO TORRES
B7: 87127 | C7: 87 | D7: ED.LONDRINA - CMEI APARECIDO NORATO CLARO | E7: CARLOS FABRI
B8: 87015 | C8: 87 | D8: ED.LONDRINA - CMEI HELENA OMETTO TORRES | E8: CARLOS FABRI
B9: 87016 | C9: 87 | D9: ED.LONDRINA - CMEI JOÃO RAMPAZZO | E9: CARLOS FABRI
B10: 87022 | C10: 87 | D10: ED.LONDRINA - CMEI MARINA SABÓIA NASCIMENTO | E10: CARLOS FABRI
B11: 87025 | C11: 87 | D11: ED.LONDRINA - CMEI MARLI MARQUES AGOSTINHO | E11: CARLOS FABRI
B12: 87027 | C12: 87 | D12: ED.LONDRINA - CMEI PASTOR FRANCISCO SEIXAS | E12: CARLOS FABRI
B13: 87037 | C13: 87 | D13: ED.LONDRINA - CMEI VILMA ELIZA COLOMBO RIBEIRO | E13: CARLOS FABRI
... B349: 308005 | C349: 308 | D349: FUNEAS - HOSP. REG. NORTE PIONEIRO - HRNP - SANTO ANTONIO DA PLATINA | E349: FERNANDO SANTOS

Sheet TED
A1: CODIGO | B1: NOME | C1: SUPERVISOR | D1: DPTO | E1: CENTRO | F1: LOCAL | G1: HORAS MÊS | H1: ADMISSAO | I1: CARGO | J1: STATUS | K1: SITUACAO
A2: 8169 | B2: AMANDA STHEFANNE MACEDO LEMOS | C2: =IFERROR(VLOOKUP(TED[[#This Row],[CENTRO]],'CENTRO DE CUSTO'!B:E,4,FALSE)," ") -> DENISE | D2: 28 | E2: 28000 | F2: ADMINISTRATIVO - LONDRINA | G2: 220 | H2: 42716 | I2: ANALISTA ADMINISTRATIVO | J2: =IF(OR(TED[[#This Row],[SITUACAO]]=1,TED[[#This Row],[SITUACAO]]=9,TED[[#This Row],[SITUACAO]]=18),"ATIVO","AFASTADO") -> ATIVO | K2: 1
A3: 46874 | B3: ANA LUIZA MAYUMI CORDEIRO TANNO | C3: =IFERROR(VLOOKUP(TED[[#This Row],[CENTRO]],'CENTRO DE CUSTO'!B:E,4,FALSE)," ") -> DENISE | D3: 28 | E3: 28000 | F3: ADMINISTRATIVO - LONDRINA | G3: 100 | H3: 46195 | I3: MENOR APRENDIZ | J3: =IF(OR(TED[[#This Row],[SITUACAO]]=1,TED[[#This Row],[SITUACAO]]=9,TED[[#This Row],[SITUACAO]]=18),"ATIVO","AFASTADO") -> ATIVO | K3: 1
A4: 42332 | B4: BRUNO VINICIOS THEODORO CORDEIRO | C4: =IFERROR(VLOOKUP(TED[[#This Row],[CENTRO]],'CENTRO DE CUSTO'!B:E,4,FALSE)," ") -> DENISE | D4: 28 | E4: 28000 | F4: ADMINISTRATIVO - LONDRINA | G4: 220 | H4: 45980 | I4: COORDENADOR (A) | J4: =IF(OR(TED[[#This Row],[SITUACAO]]=1,TED[[#This Row],[SITUACAO]]=9,TED[[#This Row],[SITUACAO]]=18),"ATIVO","AFASTADO") -> ATIVO | K4: 1
A5: 33482 | B5: BRYAN GABRIEL RIBEIRO DOS SANTOS | C5: =IFERROR(VLOOKUP(TED[[#This Row],[CENTRO]],'CENTRO DE CUSTO'!B:E,4,FALSE)," ") -> DENISE | D5: 28 | E5: 28000 | F5: ADMINISTRATIVO - LONDRINA | G5: 220 | H5: 45512 | I5: ANALISTA ADMINISTRATIVO | J5: =IF(OR(TED[[#This Row],[SITUACAO]]=1,TED[[#This Row],[SITUACAO]]=9,TED[[#This Row],[SITUACAO]]=18),"ATIVO","AFASTADO") -> ATIVO | K5: 1
A6: 36981 | B6: CAMILA VITORIA BRAZ FARIAS | C6: =IFERROR(VLOOKUP(TED[[#This Row],[CENTRO]],'CENTRO DE CUSTO'!B:E,4,FALSE)," ") -> DENISE | D6: 28 | E6: 28000 | F6: ADMINISTRATIVO - LONDRINA | G6: 220 | H6: 45705 | I6: ASSISTENTE DE DP BASE | J6: =IF(OR(TED[[#This Row],[SITUACAO]]=1,TED[[#This Row],[SITUACAO]]=9,TED[[#This Row],[SITUACAO]]=18),"ATIVO","AFASTADO") -> ATIVO | K6: 1
A7: 43442 | B7: CLEVERTON RODRIGO DA CUNHA | C7: =IFERROR(VLOOKUP(TED[[#This Row],[CENTRO]],'CENTRO DE CUSTO'!B:E,4,FALSE)," ") -> DENISE | D7: 28 | E7: 28000 | F7: ADMINISTRATIVO - LONDRINA | G7: 220 | H7: 46055 | I7: SUPERVISOR(A) | J7: =IF(OR(TED[[#This Row],[SITUACAO]]=1,TED[[#This Row],[SITUACAO]]=9,TED[[#This Row],[SITUACAO]]=18),"ATIVO","AFASTADO") -> ATIVO | K7: 1
A8: 40139 | B8: EDUCIANDRA DA SILVA DONAIRE | C8: =IFERROR(VLOOKUP(TED[[#This Row],[CENTRO]],'CENTRO DE CUSTO'!B:E,4,FALSE)," ") -> DENISE | D8: 28 | E8: 28000 | F8: ADMINISTRATIVO - LONDRINA | G8: 220 | H8: 45901 | I8: SERVENTE - INSALUB. 40% | J8: =IF(OR(TED[[#This Row],[SITUACAO]]=1,TED[[#This Row],[SITUACAO]]=9,TED[[#This Row],[SITUACAO]]=18),"ATIVO","AFASTADO") -> ATIVO | K8: 1
A9: 5138 | B9: ELAINE SCHIAVINATO FERNANDES PALIARINI | C9: =IFERROR(VLOOKUP(TED[[#This Row],[CENTRO]],'CENTRO DE CUSTO'!B:E,4,FALSE)," ") -> DENISE | D9: 28 | E9: 28000 | F9: ADMINISTRATIVO - LONDRINA | G9: 220 | H9: 42309 | I9: COORDENADOR (A) DE FILIAL II | J9: =IF(OR(TED[[#This Row],[SITUACAO]]=1,TED[[#This Row],[SITUACAO]]=9,TED[[#This Row],[SITUACAO]]=18),"ATIVO","AFASTADO") -> ATIVO | K9: 1
A10: 29260 | B10: GABRIELLY RIBEIRO VICENTE FERREIRA | C10: =IFERROR(VLOOKUP(TED[[#This Row],[CENTRO]],'CENTRO DE CUSTO'!B:E,4,FALSE)," ") -> DENISE | D10: 28 | E10: 28000 | F10: ADMINISTRATIVO - LONDRINA | G10: 220 | H10: 45251 | I10: ASSISTENTE ADMINISTRATIVO | J10: =IF(OR(TED[[#This Row],[SITUACAO]]=1,TED[[#This Row],[SITUACAO]]=9,TED[[#This Row],[SITUACAO]]=18),"ATIVO","AFASTADO") -> ATIVO | K10: 1
A11: 46882 | B11: GUILHERME BARBOSA ANDRE BREVE | C11: =IFERROR(VLOOKUP(TED[[#This Row],[CENTRO]],'CENTRO DE CUSTO'!B:E,4,FALSE)," ") -> DENISE | D11: 28 | E11: 28000 | F11: ADMINISTRATIVO - LONDRINA | G11: 220 | H11: 46195 | I11: ASSISTENTE ADMINISTRATIVO | J11: =IF(OR(TED[[#This Row],[SITUACAO]]=1,TED[[#This Row],[SITUACAO]]=9,TED[[#This Row],[SITUACAO]]=18),"ATIVO","AFASTADO") -> ATIVO | K11: 1
A12: 43374 | B12: HILARY CAROLINE FREIRE DE ABREU | C12: =IFERROR(VLOOKUP(TED[[#This Row],[CENTRO]],'CENTRO DE CUSTO'!B:E,4,FALSE)," ") -> DENISE | D12: 28 | E12: 28000 | F12: ADMINISTRATIVO - LONDRINA | G12: 100 | H12: 46048 | I12: MENOR APRENDIZ | J12: =IF(OR(TED[[#This Row],[SITUACAO]]=1,TED[[#This Row],[SITUACAO]]=9,TED[[#This Row],[SITUACAO]]=18),"ATIVO","AFASTADO") -> ATIVO | K12: 1
A13: 18547 | B13: JEFFERSON ANTONIO CARDOSO | C13: =IFERROR(VLOOKUP(TED[[#This Row],[CENTRO]],'CENTRO DE CUSTO'!B:E,4,FALSE)," ") -> DENISE | D13: 28 | E13: 28000 | F13: ADMINISTRATIVO - LONDRINA | G13: 220 | H13: 44578 | I13: SUPERVISOR(A) | J13: =IF(OR(TED[[#This Row],[SITUACAO]]=1,TED[[#This Row],[SITUACAO]]=9,TED[[#This Row],[SITUACAO]]=18),"ATIVO","AFASTADO") -> ATIVO | K13: 1
... A2307: 45785 | B2307: VICTOR EDUARDO ALVES MIRANDA | C2307: =IFERROR(VLOOKUP(TED[[#This Row],[CENTRO]],'CENTRO DE CUSTO'!B:E,4,FALSE)," ") | D2307: 312 | E2307: 312020 | F2307: TRIB. DE JUSTIÇA PR/REGIÃO PONTA GROSSA - TELEMACO BORBA | G2307: 220 | H2307: 46167 | I2307: RECEPCIONISTA | J2307: =IF(OR(TED[[#This Row],[SITUACAO]]=1,TED[[#This Row],[SITUACAO]]=9,TED[[#This Row],[SITUACAO]]=18),"ATIVO","AFASTADO") -> ATIVO | K2307: 1
